setup.py
binomial_gaussian_probability/Binomialdistribution.py
binomial_gaussian_probability/Gaussiandistribution.py
binomial_gaussian_probability/Generaldistribution.py
binomial_gaussian_probability/__init__.py
binomial_gaussian_probability.egg-info/PKG-INFO
binomial_gaussian_probability.egg-info/SOURCES.txt
binomial_gaussian_probability.egg-info/dependency_links.txt
binomial_gaussian_probability.egg-info/not-zip-safe
binomial_gaussian_probability.egg-info/top_level.txt