Metadata-Version: 1.0
Name: binomial-gaussian-probability
Version: 0.1
Summary: Gaussian and Binomial distributions
Home-page: UNKNOWN
Author: Oluwatosin Obisan
Author-email: obisanoluwatosin@gmail.com
License: UNKNOWN
Platform: UNKNOWN
